graphql_schema/.gitignore
graphql_schema/__init__.py
graphql_schema/gen_schema.py
graphql_schema/schema.py
graphql_schema/schema_query.gql
nac/.mypy_cache/.gitignore
nac/.mypy_cache/3.11/@plugins_snapshot.json
nac/.mypy_cache/3.11/_ast.data.json
nac/.mypy_cache/3.11/_ast.meta.json
nac/.mypy_cache/3.11/_codecs.data.json
nac/.mypy_cache/3.11/_codecs.meta.json
nac/.mypy_cache/3.11/_collections_abc.data.json
nac/.mypy_cache/3.11/_collections_abc.meta.json
nac/.mypy_cache/3.11/_ctypes.data.json
nac/.mypy_cache/3.11/_ctypes.meta.json
nac/.mypy_cache/3.11/_thread.data.json
nac/.mypy_cache/3.11/_thread.meta.json
nac/.mypy_cache/3.11/_typeshed/__init__.data.json
nac/.mypy_cache/3.11/_typeshed/__init__.meta.json
nac/.mypy_cache/3.11/_winapi.data.json
nac/.mypy_cache/3.11/_winapi.meta.json
nac/.mypy_cache/3.11/abc.data.json
nac/.mypy_cache/3.11/abc.meta.json
nac/.mypy_cache/3.11/array.data.json
nac/.mypy_cache/3.11/array.meta.json
nac/.mypy_cache/3.11/builtins.data.json
nac/.mypy_cache/3.11/builtins.meta.json
nac/.mypy_cache/3.11/codecs.data.json
nac/.mypy_cache/3.11/codecs.meta.json
nac/.mypy_cache/3.11/collections/__init__.data.json
nac/.mypy_cache/3.11/collections/__init__.meta.json
nac/.mypy_cache/3.11/collections/abc.data.json
nac/.mypy_cache/3.11/collections/abc.meta.json
nac/.mypy_cache/3.11/contextlib.data.json
nac/.mypy_cache/3.11/contextlib.meta.json
nac/.mypy_cache/3.11/ctypes/__init__.data.json
nac/.mypy_cache/3.11/ctypes/__init__.meta.json
nac/.mypy_cache/3.11/dataclasses.data.json
nac/.mypy_cache/3.11/dataclasses.meta.json
nac/.mypy_cache/3.11/email/__init__.data.json
nac/.mypy_cache/3.11/email/__init__.meta.json
nac/.mypy_cache/3.11/email/charset.data.json
nac/.mypy_cache/3.11/email/charset.meta.json
nac/.mypy_cache/3.11/email/contentmanager.data.json
nac/.mypy_cache/3.11/email/contentmanager.meta.json
nac/.mypy_cache/3.11/email/errors.data.json
nac/.mypy_cache/3.11/email/errors.meta.json
nac/.mypy_cache/3.11/email/header.data.json
argos_nac-0.1.3.dist-info/entry_points.txt
argos_nac-0.1.3.dist-info/WHEEL
argos_nac-0.1.3.dist-info/METADATA
argos_nac-0.1.3.dist-info/RECORD
